linvpy/__init__.py
linvpy/linvpy.py
linvpy/setup.py
linvpy/tests/__init__.py
linvpy/tests/generate_random.py
linvpy/tests/test.py
linvpy/tests/test_final.py
linvpy/tests/regularizedtau/__init__.py
linvpy/tests/regularizedtau/linvpy_latest.py
linvpy/tests/regularizedtau/toolboxexperiments.py
linvpy/tests/regularizedtau/toolboxinverse_latest.py
linvpy/tests/regularizedtau/toolboxutilities.py
linvpy/tests/regularizedtau/toolboxutilities_latest.py
linvpy/tests/regularizedtau/Sridge/__init__.py
linvpy/tests/regularizedtau/Sridge/matlab/__init__.py
linvpy/tests/regularizedtau/Sridge/python/__init__.py
linvpy/tests/regularizedtau/Sridge/python/sridge.py
linvpy-2.6.dist-info/DESCRIPTION.rst
linvpy-2.6.dist-info/METADATA
linvpy-2.6.dist-info/RECORD
linvpy-2.6.dist-info/WHEEL
linvpy-2.6.dist-info/metadata.json
linvpy-2.6.dist-info/top_level.txt
