Metadata-Version: 2.0
Name: linvpy
Version: 2.6
Summary: Package to solve linear inverse problems
Home-page: https://github.com/LCAV/linvpy
Author: Guillaume Beaud, Marta Martinez-Camara
Author-email: beaudguillaume@gmail.com
License: BSD
Keywords: linear inverse M-estimator Tau-estimator regression
Platform: UNKNOWN
Classifier: Development Status :: 2 - Pre-Alpha
Classifier: Programming Language :: Python :: 2
Classifier: Programming Language :: Python :: 2.6
Classifier: Programming Language :: Python :: 2.7
Requires-Dist: numpy
